flask_obscure.py
Flask_Obscure-1.0.dist-info/DESCRIPTION.rst
Flask_Obscure-1.0.dist-info/METADATA
Flask_Obscure-1.0.dist-info/RECORD
Flask_Obscure-1.0.dist-info/WHEEL
Flask_Obscure-1.0.dist-info/metadata.json
Flask_Obscure-1.0.dist-info/top_level.txt
