Metadata-Version: 2.0
Name: Flask-Obscure
Version: 1.0
Summary: Obscure numerical IDs in URLs
Home-page: http://www.github.com/jidn/flask-obscure/
Author: Clinton James
Author-email: clinton.james@anuit.com
License: Apache License 2.0
Keywords: flask,REST,obfuscate,ID
Platform: any
Classifier: Environment :: Web Environment
Classifier: Intended Audience :: Developers
Classifier: License :: OSI Approved :: Apache Software License
Classifier: Programming Language :: Python
Classifier: Programming Language :: Python :: 2.7
Classifier: Programming Language :: Python :: 3
Classifier: Topic :: Internet :: WWW/HTTP :: Dynamic Content
Classifier: Topic :: Software Development :: Libraries :: Python Modules
Requires-Dist: Flask (>=0.10)
Requires-Dist: obscure
